README.md
setup.py
abadon_sdk/__init__.py
abadon_sdk/abadon_sdk.py
abadon_sdk/env.py
abadon_sdk.egg-info/PKG-INFO
abadon_sdk.egg-info/SOURCES.txt
abadon_sdk.egg-info/dependency_links.txt
abadon_sdk.egg-info/top_level.txt
test/test_context.py