Metadata-Version: 1.2
Name: abadon-sdk
Version: 0.1.3
Summary: Abadon SDK
Home-page: https://momenta.ai
Author: MyronLu
Author-email: myronlu1005@gmail.com
License: UNKNOWN
Keywords: Abadon SDK
Platform: UNKNOWN
Classifier: Programming Language :: Python
Classifier: Programming Language :: Python :: Implementation
Classifier: Programming Language :: Python :: 2.7
Classifier: Programming Language :: Python :: 3.4
Classifier: Programming Language :: Python :: 3.5
Classifier: Programming Language :: Python :: 3.6
Classifier: Topic :: Software Development :: Libraries
Requires-Python: >=2.7
